ScaleRPy/__init__.py
ScaleRPy/man_dat.py
ScaleRPy/fitting/fit_funcs.py
ScaleRPy/formatting/__init__.py
ScaleRPy/formatting/density_contours.py
ScaleRPy/formatting/tol_colors.py
scalerpy-1.1.1.dist-info/LICENSE
scalerpy-1.1.1.dist-info/METADATA
scalerpy-1.1.1.dist-info/WHEEL
scalerpy-1.1.1.dist-info/top_level.txt
scalerpy-1.1.1.dist-info/RECORD
