Metadata-Version: 2.2
Name: ScaleRPy
Version: 1.1.1
Summary: Obtain fits to scaling relations using the ridge line method
Author-email: Bryanne McDonough <br.mcdonough@northeastern.edu>
License: 
Project-URL: repository, https://github.com/bryannemcd/ScaleRPy
Classifier: Programming Language :: Python :: 3
Requires-Python: >=3.8
License-File: LICENSE
Requires-Dist: numpy
Requires-Dist: matplotlib
Requires-Dist: scipy
